<?xml version="1.0" encoding="UTF-8"?>
<the:UZ-ac4320 xmlns:ic="animo/connection" xmlns:is="animo/relation/is" xmlns:have="animo/relation/have" xmlns:an="animo/reference" xmlns:ptrn="animo/pattern" xmlns:the="animo/instance">
    <is:UZ-ac4300/>
    <have:name>
        <ptrn:language>
            <have:lang-ru>Авансы, выданные поставщикам и подрядчикам под долгосрочные активы</have:lang-ru>
        </ptrn:language>
    </have:name>

    <have:code>43.20</have:code>
    <have:code>4320</have:code>
</the:UZ-ac4320>