<?xml version="1.0" encoding="UTF-8"?>
<the:register xmlns:ic="animo/connection" xmlns:any="animo/query/any" xmlns:an="animo/reference" xmlns:the="animo/instance">
    <xsl:stylesheet xmlns:xsl="http://www.w3.org/1999/XSL/Transform" version="2.0">
        <xsl:template match="/">
            <panel xmlns="animo/widget">
                <an:new-object>
                    <ic:uri>/an:test?xml:id</ic:uri>
                </an:new-object>
            </panel>
            <table xmlns="animo/widget">
                <columns>
                    <an:number/>
                    <an:description/>
                </columns>
                <rows>
                    <columns>
                        <an:number/>
                        <an:description/>
                    </columns>
                    <!-- query request -->
                    <any:test/>
                    <!-- query result -->
                    <ic:test xml:idref="some1">
                        <ic:number>1</ic:number>
                        <ic:description>Some test</ic:description>
                    </ic:test>
                    <ic:test xml:idref="some2">
                        <ic:description>Some test2</ic:description>
                    </ic:test>
                    <ic:test xml:idref="some3">
                        <ic:number>3</ic:number>
                    </ic:test>
                </rows>
            </table>
        </xsl:template>
    </xsl:stylesheet>
</the:register>